{"stats":{"minecraft:picked_up":{"minecraft:stripped_oak_log":2,"minecraft:crafting_table":2,"minecraft:oak_door":3,"minecraft:torch":16,"minecraft:flint":1,"minecraft:tuff":1,"minecraft:oak_log":8,"gravestone:obituary":1,"minecraft:cornflower":2,"minecraft:gunpowder":4,"minecraft:dirt":4,"minecraft:bone":5,"crittersandcompanions:dragonfly_wing":2,"minecraft:cobbled_deepslate":2,"minecraft:bone_meal":1,"darkestsouls:titanite_fragment":1,"minecraft:cobblestone":14},"minecraft:mined":{"minecraft:oak_door":3,"minecraft:fire":4,"supplementaries:gunpowder":2,"minecraft:crafting_table":2,"minecraft:cornflower":1,"minecraft:torch":6,"gravestone:gravestone":10,"minecraft:grass":20,"minecraft:grass_block":4,"minecraft:oak_log":8,"minecraft:gravel":1,"minecraft:stripped_oak_log":2,"minecraft:tall_grass":2,"minecraft:cobblestone":2,"minecraft:stone":14,"minecraft:oak_leaves":2,"minecraft:wall_torch":9},"minecraft:killed_by":{"darkestsouls:beast_patient":1,"darkestsouls:skeleton_spear":1,"darkestsouls:cloaked_beast_patient":1},"minecraft:crafted":{"minecraft:oak_planks":24,"minecraft:crafting_table":1,"minecraft:stick":12,"minecraft:wooden_pickaxe":1,"minecraft:stone_pickaxe":1,"minecraft:furnace":1,"minecraft:stone_axe":1},"minecraft:used":{"minecraft:oak_log":2,"minecraft:oak_planks":1,"minecraft:wooden_pickaxe":17,"minecraft:torch":1,"minecraft:stone_axe":5,"minecraft:wooden_sword":5,"minecraft:oak_door":3,"minecraft:gunpowder":2,"farmersdelight:onion":7,"minecraft:dirt":4,"supplementaries:ash":1,"minecraft:crafting_table":2,"minecraft:furnace":1,"minecraft:stripped_oak_log":1,"minecraft:tuff":1,"minecraft:cobbled_deepslate":2},"minecraft:dropped":{"minecraft:gunpowder":2,"alexsmobs:animal_dictionary":1,"darkestsouls:titanite_fragment":1,"minecraft:cornflower":2,"minecraft:bone_meal":1,"gravestone:obituary":2,"minecraft:wooden_pickaxe":1,"minecraft:bone":5,"minecraft:flint":1},"minecraft:custom":{"minecraft:time_since_rest":1377,"minecraft:sprint_one_cm":176813,"minecraft:damage_taken":5463,"minecraft:walk_one_cm":108696,"minecraft:mob_kills":5,"minecraft:drop":16,"minecraft:damage_dealt":1216,"minecraft:fly_one_cm":364091,"minecraft:talked_to_villager":30,"minecraft:swim_one_cm":3125,"minecraft:interact_with_crafting_table":4,"minecraft:open_chest":21,"minecraft:crouch_one_cm":1854,"minecraft:play_time":58627,"minecraft:deaths":15,"minecraft:sneak_time":523,"minecraft:walk_under_water_one_cm":11093,"minecraft:jump":1553,"minecraft:leave_game":4,"minecraft:walk_on_water_one_cm":23178,"minecraft:time_since_death":1344,"minecraft:total_world_time":58627,"minecraft:fall_one_cm":85123},"minecraft:killed":{"minecraft:villager":2,"crittersandcompanions:dragonfly":2}},"DataVersion":3465}